LICENSE
README.md
cities.json
countries+cities.json
countries+states+cities.json
countries+states.json
countries.json
regions.json
setup.py
states+cities.json
states.json
subregions.json
./py_countries_states_cities_database/__init__.py
./py_countries_states_cities_database/cities.json
./py_countries_states_cities_database/countries+cities.json
./py_countries_states_cities_database/countries+states+cities.json
./py_countries_states_cities_database/countries+states.json
./py_countries_states_cities_database/countries.json
./py_countries_states_cities_database/interface.py
./py_countries_states_cities_database/nmig.config.json
./py_countries_states_cities_database/regions.json
./py_countries_states_cities_database/states+cities.json
./py_countries_states_cities_database/states.json
./py_countries_states_cities_database/subregions.json
py_countries_states_cities_database/__init__.py
py_countries_states_cities_database/cities.json
py_countries_states_cities_database/countries+cities.json
py_countries_states_cities_database/countries+states+cities.json
py_countries_states_cities_database/countries+states.json
py_countries_states_cities_database/countries.json
py_countries_states_cities_database/interface.py
py_countries_states_cities_database/regions.json
py_countries_states_cities_database/states+cities.json
py_countries_states_cities_database/states.json
py_countries_states_cities_database/subregions.json
py_countries_states_cities_database.egg-info/PKG-INFO
py_countries_states_cities_database.egg-info/SOURCES.txt
py_countries_states_cities_database.egg-info/dependency_links.txt
py_countries_states_cities_database.egg-info/requires.txt
py_countries_states_cities_database.egg-info/top_level.txt
py_countries_states_cities_database/../cities.json
py_countries_states_cities_database/../countries+cities.json
py_countries_states_cities_database/../countries+states+cities.json
py_countries_states_cities_database/../countries+states.json
py_countries_states_cities_database/../countries.json
py_countries_states_cities_database/../regions.json
py_countries_states_cities_database/../states+cities.json
py_countries_states_cities_database/../states.json
py_countries_states_cities_database/../subregions.json