Metadata-Version: 2.1
Name: py-countries-states-cities-database
Version: 2.2.13
Summary: A Python package to get countries, states and cities information
Home-page: https://github.com/umer2001/py_countries_states_cities_database
Author: Umer Farooq
Author-email: umer2001.uf@gmail.com
License: MIT
Keywords: countries states cities database
Platform: UNKNOWN
Classifier: Development Status :: 3 - Alpha
Classifier: Intended Audience :: Developers
Classifier: License :: OSI Approved :: MIT License
Classifier: Programming Language :: Python :: 3
Classifier: Programming Language :: Python :: 3.6
Classifier: Programming Language :: Python :: 3.7
Classifier: Programming Language :: Python :: 3.8
Classifier: Programming Language :: Python :: 3.9
Classifier: Programming Language :: Python :: 3.10
Provides-Extra: dev
License-File: LICENSE
